sun_diffusion/__init__.py
sun_diffusion/__main__.py
sun_diffusion/action.py
sun_diffusion/analysis.py
sun_diffusion/canon.py
sun_diffusion/devices.py
sun_diffusion/diffusion.py
sun_diffusion/gens.py
sun_diffusion/heat.py
sun_diffusion/irreps.py
sun_diffusion/linalg.py
sun_diffusion/sun.py
sun_diffusion/utils.py
sun_diffusion-1.0.0.dist-info/licenses/LICENSE
sun_diffusion-1.0.0.dist-info/METADATA
sun_diffusion-1.0.0.dist-info/WHEEL
sun_diffusion-1.0.0.dist-info/top_level.txt
sun_diffusion-1.0.0.dist-info/RECORD
