Metadata-Version: 2.4
Name: sun_diffusion
Version: 1.0.0
Summary: Diffusion models for SU(N) degrees of freedom.
Author-email: Gurtej Kanwar <gurtejkanwar@gmail.com>, Octavio Vega <vega00087@gmail.com>
License: MIT License
Project-URL: Repository, https://github.com/ovega14/sun_diffusion
Project-URL: Paper, https://arxiv.org/abs/2512.19877
Project-URL: Documentation, https://ovega14.github.io/sun_diffusion
Classifier: Programming Language :: Python :: 3
Classifier: License :: OSI Approved :: MIT License
Classifier: Operating System :: OS Independent
Requires-Python: >=3.10
License-File: LICENSE
Requires-Dist: numpy<2,>=1.24
Requires-Dist: torch>=2.0.0
Provides-Extra: gpu
Requires-Dist: torch; extra == "gpu"
Provides-Extra: notebooks
Requires-Dist: jupyter; extra == "notebooks"
Requires-Dist: matplotlib; extra == "notebooks"
Requires-Dist: tqdm<5.0,>=4.65; extra == "notebooks"
Requires-Dist: ipywidgets==7.7.2; extra == "notebooks"
Provides-Extra: docs
Requires-Dist: sphinx>=7.0; extra == "docs"
Requires-Dist: furo; extra == "docs"
Requires-Dist: myst-parser; extra == "docs"
Requires-Dist: sphinx-autodoc-typehints; extra == "docs"
Requires-Dist: sphinx-copybutton; extra == "docs"
Dynamic: license-file
